quantfe/__init__.py
quantfe/market/__init__.py
quantfe/market/curves/discount_curve.py
quantfe/market/curves/discount_curve_flat.py
quantfe/market/curves/discount_curve_zero.py
quantfe/market/curves/interpolator.py
quantfe/market/volatility/fx_volatility_surface.py
quantfe/models/__init__.py
quantfe/models/bachelier.py
quantfe/models/black.py
quantfe/models/black_scholes.py
quantfe/models/black_scholes_analytic.py
quantfe/models/equity_crr_tree.py
quantfe/models/finite_difference.py
quantfe/models/hw_tree.py
quantfe/models/model.py
quantfe/models/option_implied_dbn.py
quantfe/models/process_simulator.py
quantfe/models/sabr.py
quantfe/models/volatility_fns.py
quantfe/products/__init__.py
quantfe/products/bonds/bond.py
quantfe/products/bonds/bond_callable.py
quantfe/products/bonds/bond_convertible.py
quantfe/products/bonds/bond_market.py
quantfe/products/bonds/bond_zero.py
quantfe/products/bonds/bond_zero_curve.py
quantfe/products/credit/cds.py
quantfe/products/equity/equity_option.py
quantfe/products/fx/fx_forward.py
quantfe/products/fx/fx_mkt_conventions.py
quantfe/products/fx/fx_TRF.py
quantfe/products/fx/fx_vanilla_option.py
quantfe/products/fx/type.py
quantfe/products/rates/ibor_deposit.py
quantfe/products/rates/ois.py
quantfe/products/rates/swap/fixed_fixed_xccy_swap.py
quantfe/products/rates/swap/fixed_ibor_xccy_swap.py
quantfe/products/rates/swap/ibor_ibor_basis_swap.py
quantfe/products/rates/swap/ibor_ibor_xccy_swap.py
quantfe/products/rates/swap_fixed_leg.py
quantfe/products/rates/swap_floating_leg.py
quantfe/products/rates/swap_overnight_leg.py
quantfe/utils/__init__.py
quantfe/utils/calendar.py
quantfe/utils/currency.py
quantfe/utils/date.py
quantfe/utils/day_count.py
quantfe/utils/distribution.py
quantfe/utils/error.py
quantfe/utils/frequency.py
quantfe/utils/global_types.py
quantfe/utils/global_vars.py
quantfe/utils/helpers.py
quantfe/utils/holidays.json
quantfe/utils/qmath.py
quantfe/utils/schedule.py
quantfe/utils/singleton.py
quantfe-0.1.1.dist-info/METADATA
quantfe-0.1.1.dist-info/WHEEL
quantfe-0.1.1.dist-info/RECORD
